oscr-2.1.1.data/scripts/oscr
oscrcore/__init__.py
oscrcore/arguments.py
oscrcore/auth.py
oscrcore/comment.py
oscrcore/globals.py
oscrcore/ini.py
oscrcore/log.py
oscrcore/main.py
oscrcore/misc.py
oscrcore/settings.py
oscrcore/statistics.py
oscr-2.1.1.dist-info/LICENSE
oscr-2.1.1.dist-info/METADATA
oscr-2.1.1.dist-info/WHEEL
oscr-2.1.1.dist-info/top_level.txt
oscr-2.1.1.dist-info/RECORD
