Metadata-Version: 2.1
Name: oscr
Version: 2.1.1
Summary: A utility allowing users to delete blacklisted comments from their Reddit profile once they have passed a cutoff time.
Home-page: https://github.com/MurdoMaclachlan/oscr
Author: Murdo Maclachlan
Author-email: murdomaclachlan@duck.com
License: GPLv3+
Platform: UNKNOWN
Classifier: Programming Language :: Python :: 3
Classifier: License :: OSI Approved :: GNU General Public License v3 or later (GPLv3+)
Classifier: Operating System :: OS Independent
License-File: LICENSE
Requires-Dist: alive-progress (>=1.6.1)
Requires-Dist: colored
Requires-Dist: configparser
Requires-Dist: praw (>=7.1.2)
